somatorio_alisson_rodrigov2/__init__.py
somatorio_alisson_rodrigov2/pacoteteste.py
somatorio_alisson_rodrigov2-0.0.1.dist-info/LICENSE
somatorio_alisson_rodrigov2-0.0.1.dist-info/METADATA
somatorio_alisson_rodrigov2-0.0.1.dist-info/WHEEL
somatorio_alisson_rodrigov2-0.0.1.dist-info/top_level.txt
somatorio_alisson_rodrigov2-0.0.1.dist-info/RECORD
